setup.py
brynq_sdk_personio/__init__.py
brynq_sdk_personio/absences.py
brynq_sdk_personio/attendances.py
brynq_sdk_personio/compensations.py
brynq_sdk_personio/custom_reports.py
brynq_sdk_personio/documents.py
brynq_sdk_personio/employees.py
brynq_sdk_personio/employments.py
brynq_sdk_personio/persons.py
brynq_sdk_personio.egg-info/PKG-INFO
brynq_sdk_personio.egg-info/SOURCES.txt
brynq_sdk_personio.egg-info/dependency_links.txt
brynq_sdk_personio.egg-info/not-zip-safe
brynq_sdk_personio.egg-info/requires.txt
brynq_sdk_personio.egg-info/top_level.txt
brynq_sdk_personio/schemas/absence.py
brynq_sdk_personio/schemas/company.py
brynq_sdk_personio/schemas/compensation.py
brynq_sdk_personio/schemas/employment.py
brynq_sdk_personio/schemas/person.py