Metadata-Version: 1.0
Name: brynq-sdk-personio
Version: 2.1.0
Summary: Personio wrapper from BrynQ
Home-page: UNKNOWN
Author: BrynQ
Author-email: support@brynq.com
License: BrynQ License
Platform: UNKNOWN
